{
  "polar_user": "https://polaraccesslink.com/v3/users/64113897",
  "date": "2026-06-18",
  "heart_rate_avg": 55,
  "beat_to_beat_avg": 1073,
  "heart_rate_variability_avg": 47,
  "breathing_rate_avg": 13.0,
  "nightly_recharge_status": 3,
  "ans_charge": -2.7,
  "ans_charge_status": 2,
  "hrv_samples": {
    "00:35": 59,
    "00:40": 39,
    "00:45": 68,
    "00:50": 57,
    "00:55": 36,
    "01:00": 32,
    "01:05": 34,
    "01:10": 36,
    "01:15": 43,
    "01:20": 36,
    "01:25": 52,
    "01:30": 28,
    "01:35": 23,
    "01:40": 36,
    "01:45": 23,
    "01:50": 35,
    "01:55": 26,
    "02:00": 26,
    "02:05": 23,
    "02:10": 22,
    "02:15": 22,
    "02:20": 39,
    "02:25": 49,
    "02:30": 67,
    "02:35": 58,
    "02:40": 49,
    "02:45": 59,
    "02:50": 64,
    "02:55": 41,
    "03:00": 38,
    "03:05": 41,
    "03:10": 49,
    "03:15": 44,
    "03:20": 38,
    "03:25": 45,
    "03:30": 31,
    "03:35": 42,
    "03:40": 67,
    "03:45": 69,
    "03:50": 64,
    "03:55": 70,
    "04:00": 39,
    "04:05": 62,
    "04:10": 52,
    "04:15": 88,
    "04:20": 62,
    "04:25": 50,
    "04:30": 37,
    "04:35": 36,
    "04:40": 63,
    "04:45": 61,
    "04:50": 51,
    "04:55": 26,
    "05:00": 38,
    "05:05": 42,
    "05:10": 52,
    "05:15": 39,
    "05:20": 53,
    "05:25": 43,
    "05:30": 63,
    "05:36": 70,
    "05:41": 63,
    "05:46": 62,
    "05:51": 59,
    "05:56": 46,
    "06:01": 48,
    "06:06": 41,
    "06:11": 44
  },
  "breathing_samples": {
    "00:32": 16.3,
    "00:37": 15.6,
    "00:42": 15.0,
    "00:47": 13.9,
    "00:52": 13.0,
    "00:57": 13.1,
    "01:02": 13.2,
    "01:07": 11.6,
    "01:12": 13.4,
    "01:17": 11.3,
    "01:22": 11.8,
    "01:27": 11.9,
    "01:32": 11.7,
    "01:37": 10.1,
    "01:42": 13.0,
    "01:47": 12.4,
    "01:52": 12.4,
    "01:57": 11.7,
    "02:02": 11.6,
    "02:07": 10.2,
    "02:12": 10.9,
    "02:17": 11.9,
    "02:22": 11.4,
    "02:27": 14.1,
    "02:32": 16.4,
    "02:37": 12.6,
    "02:42": 14.1,
    "02:47": 13.9,
    "02:52": 12.4,
    "02:57": 14.3,
    "03:02": 15.5,
    "03:07": 11.1,
    "03:12": 14.6,
    "03:17": 13.4,
    "03:22": 14.2,
    "03:27": 12.8,
    "03:32": 12.6,
    "03:37": 13.7,
    "03:42": 13.1,
    "03:47": 16.5,
    "03:52": 15.9,
    "03:57": 13.4,
    "04:02": 12.1,
    "04:07": 11.5,
    "04:12": 13.2,
    "04:17": 16.3,
    "04:22": 14.9,
    "04:27": 13.9,
    "04:32": 12.6,
    "04:37": 12.1,
    "04:42": 13.5,
    "04:47": 12.1,
    "04:52": 11.5,
    "04:57": 12.3,
    "05:02": 13.7,
    "05:07": 14.5,
    "05:12": 11.5,
    "05:17": 13.2,
    "05:22": 13.1,
    "05:27": 12.7,
    "05:32": 14.5,
    "05:37": 15.4,
    "05:42": 16.9,
    "05:47": 16.4,
    "05:52": 13.6,
    "05:57": 12.8,
    "06:02": 12.5,
    "06:07": 11.9,
    "06:12": 14.0
  }
}